playlist_manager/__init__.py
playlist_manager/__main__.py
playlist_manager/utils.py
playlist_manager/api/app.py
playlist_manager/concurency/load_initial_data.py
playlist_manager/core/entities.py
playlist_manager/core/manager.py
playlist_manager/db/crud.py
playlist_manager/db/database.py
playlist_manager/db/models.py
playlist_manager_star-0.1.0.dist-info/METADATA
playlist_manager_star-0.1.0.dist-info/WHEEL
playlist_manager_star-0.1.0.dist-info/top_level.txt
playlist_manager_star-0.1.0.dist-info/RECORD
