Metadata-Version: 2.4
Name: playlist-manager-star
Version: 0.1.0
Summary: Advanced Playlist Manager
Author: Star
Requires-Python: >=3.9
Requires-Dist: fastapi
Requires-Dist: sqlalchemy
Requires-Dist: requests
Requires-Dist: mypy
Requires-Dist: flake8
